arrayfire/__init__.py
arrayfire/array_object.py
arrayfire/dtypes.py
arrayfire/py.typed
arrayfire/version.py
arrayfire/array_api/__init__.py
arrayfire/array_api/_array_object.py
arrayfire/array_api/_constants.py
arrayfire/array_api/_creation_function.py
arrayfire/array_api/_data_type_functions.py
arrayfire/array_api/_dtypes.py
arrayfire/array_api/_elementwise_functions.py
arrayfire/array_api/_indexing_functions.py
arrayfire/array_api/_manipulation_functions.py
arrayfire/array_api/_searching_functions.py
arrayfire/array_api/_set_functions.py
arrayfire/array_api/_sorting_functions.py
arrayfire/array_api/_statistical_functions.py
arrayfire/array_api/_utility_functions.py
arrayfire/array_api/tests/__init__.py
arrayfire/library/__init__.py
arrayfire/library/array_functions.py
arrayfire/library/computer_vision.py
arrayfire/library/constants.py
arrayfire/library/device.py
arrayfire/library/features.py
arrayfire/library/image_processing.py
arrayfire/library/input_and_output.py
arrayfire/library/interface_functions.py
arrayfire/library/linear_algebra.py
arrayfire/library/machine_learning.py
arrayfire/library/mathematical_functions.py
arrayfire/library/random.py
arrayfire/library/signal_processing.py
arrayfire/library/statistics.py
arrayfire/library/utils.py
arrayfire/library/vector_algorithms.py
arrayfire_py-0.1.0.dist-info/licenses/LICENSE
arrayfire_py-0.1.0.dist-info/METADATA
arrayfire_py-0.1.0.dist-info/WHEEL
arrayfire_py-0.1.0.dist-info/entry_points.txt
arrayfire_py-0.1.0.dist-info/top_level.txt
arrayfire_py-0.1.0.dist-info/RECORD
