Metadata-Version: 2.4
Name: arrayfire-py
Version: 0.1.0
Summary: ArrayFire Python
Maintainer-email: ArrayFire <technical@arrayfire.com>
License-Expression: BSD-3-Clause
Project-URL: Homepage, http://arrayfire.com
Project-URL: General Documentation, https://arrayfire.org/docs/index.htm
Keywords: arrayfire,parallel computing,high performance computing,hpc,gpu,cpu,opencl,cuda,oneapi,python,wrapper
Classifier: Intended Audience :: Developers
Classifier: Intended Audience :: Science/Research
Classifier: Development Status :: 5 - Production/Stable
Classifier: Programming Language :: Python
Classifier: Programming Language :: Python :: 3
Classifier: Programming Language :: Python :: 3.10
Classifier: Topic :: Scientific/Engineering
Classifier: Topic :: Scientific/Engineering :: Artificial Intelligence
Classifier: Topic :: Scientific/Engineering :: Information Analysis
Classifier: Topic :: Scientific/Engineering :: Mathematics
Classifier: Topic :: Software Development :: Libraries
Requires-Python: >=3.10
License-File: LICENSE
Requires-Dist: arrayfire-binary-python-wrapper~=0.8.0
Provides-Extra: benchmarks
Requires-Dist: numpy~=1.26.4; extra == "benchmarks"
Dynamic: license-file
